{
  "_date": "2025-01-30 20:30:09.814527",
  "_total": 92491,
  "_total_diff": 622,
  "barbet": 508,
  "barbet_diff": 0,
  "blueline": 23561,
  "blueline_diff": 35,
  "bonito": 3001,
  "bonito_diff": 5,
  "bramble": 3196,
  "bramble_diff": 142,
  "coral": 5931,
  "coral_diff": 48,
  "crosshatch": 14140,
  "crosshatch_diff": 8,
  "flame": 5665,
  "flame_diff": 5,
  "hanoip": 754,
  "hanoip_diff": 1,
  "liber": 2497,
  "liber_diff": 0,
  "miatoll": 361,
  "miatoll_diff": 35,
  "payton": 155,
  "payton_diff": 1,
  "redfin": 14080,
  "redfin_diff": 116,
  "rosemary": 792,
  "rosemary_diff": 21,
  "sargo": 6424,
  "sargo_diff": 20,
  "sunfish": 7667,
  "sunfish_diff": 109,
  "taimen": 4912,
  "taimen_diff": 132,
  "walleye": 0,
  "walleye_diff": 0
}