{
  "_date": "2025-06-12 20:35:53.535283",
  "_total": 161475,
  "_total_diff": 492,
  "barbet": 3174,
  "barbet_diff": 25,
  "blueline": 39002,
  "blueline_diff": 230,
  "bonito": 5051,
  "bonito_diff": 1,
  "bramble": 5637,
  "bramble_diff": 9,
  "coral": 10775,
  "coral_diff": 4,
  "crosshatch": 17769,
  "crosshatch_diff": 4,
  "flame": 9653,
  "flame_diff": 18,
  "hanoip": 6205,
  "hanoip_diff": 112,
  "liber": 4668,
  "liber_diff": 1,
  "miatoll": 361,
  "miatoll_diff": 35,
  "payton": 575,
  "payton_diff": 4,
  "redfin": 20645,
  "redfin_diff": 4,
  "rosemary": 792,
  "rosemary_diff": 21,
  "sargo": 10216,
  "sargo_diff": 2,
  "sunfish": 18515,
  "sunfish_diff": 31,
  "taimen": 9590,
  "taimen_diff": 47,
  "walleye": 0,
  "walleye_diff": 0
}