{
  "_date": "2025-07-28 20:40:25.950530",
  "_total": 206949,
  "_total_diff": 609,
  "barbet": 5148,
  "barbet_diff": 1,
  "blueline": 52173,
  "blueline_diff": 107,
  "bonito": 5561,
  "bonito_diff": 1,
  "bramble": 6843,
  "bramble_diff": 17,
  "coral": 13153,
  "coral_diff": 15,
  "crosshatch": 21126,
  "crosshatch_diff": 92,
  "flame": 11549,
  "flame_diff": 5,
  "hanoip": 7878,
  "hanoip_diff": 11,
  "liber": 5752,
  "liber_diff": 15,
  "miatoll": 361,
  "miatoll_diff": 35,
  "payton": 789,
  "payton_diff": 0,
  "redfin": 27234,
  "redfin_diff": 41,
  "rosemary": 792,
  "rosemary_diff": 21,
  "sargo": 11999,
  "sargo_diff": 172,
  "sunfish": 23136,
  "sunfish_diff": 129,
  "taimen": 14608,
  "taimen_diff": 3,
  "walleye": 0,
  "walleye_diff": 0
}