{
  "_date": "2025-06-04 20:29:28.177832",
  "_total": 158362,
  "_total_diff": 204,
  "barbet": 3113,
  "barbet_diff": 0,
  "blueline": 38144,
  "blueline_diff": 17,
  "bonito": 5042,
  "bonito_diff": 0,
  "bramble": 5553,
  "bramble_diff": 8,
  "coral": 10603,
  "coral_diff": 0,
  "crosshatch": 17611,
  "crosshatch_diff": 5,
  "flame": 9410,
  "flame_diff": 0,
  "hanoip": 5942,
  "hanoip_diff": 3,
  "liber": 4622,
  "liber_diff": 79,
  "miatoll": 361,
  "miatoll_diff": 35,
  "payton": 569,
  "payton_diff": 0,
  "redfin": 20107,
  "redfin_diff": 6,
  "rosemary": 792,
  "rosemary_diff": 21,
  "sargo": 10135,
  "sargo_diff": 3,
  "sunfish": 18333,
  "sunfish_diff": 82,
  "taimen": 9178,
  "taimen_diff": 1,
  "walleye": 0,
  "walleye_diff": 0
}