{
  "_date": "2025-06-24 20:35:34.847549",
  "_total": 182984,
  "_total_diff": 411,
  "barbet": 3429,
  "barbet_diff": 2,
  "blueline": 50109,
  "blueline_diff": 15,
  "bonito": 5204,
  "bonito_diff": 2,
  "bramble": 5863,
  "bramble_diff": 1,
  "coral": 10250,
  "coral_diff": 7,
  "crosshatch": 18992,
  "crosshatch_diff": 33,
  "flame": 9931,
  "flame_diff": 111,
  "hanoip": 6711,
  "hanoip_diff": 107,
  "liber": 5105,
  "liber_diff": 10,
  "miatoll": 361,
  "miatoll_diff": 35,
  "payton": 689,
  "payton_diff": 6,
  "redfin": 24486,
  "redfin_diff": 32,
  "rosemary": 792,
  "rosemary_diff": 21,
  "sargo": 10914,
  "sargo_diff": 14,
  "sunfish": 19257,
  "sunfish_diff": 32,
  "taimen": 12044,
  "taimen_diff": 39,
  "walleye": 0,
  "walleye_diff": 0
}