{
  "_date": "2025-05-27 20:34:22.911351",
  "_total": 197194,
  "_total_diff": 4080,
  "barbet": 2833,
  "barbet_diff": 26,
  "blueline": 46478,
  "blueline_diff": 3755,
  "bonito": 6363,
  "bonito_diff": 1,
  "bramble": 7361,
  "bramble_diff": 32,
  "coral": 13183,
  "coral_diff": 34,
  "crosshatch": 24207,
  "crosshatch_diff": 28,
  "flame": 12776,
  "flame_diff": 5,
  "hanoip": 5620,
  "hanoip_diff": 41,
  "liber": 6117,
  "liber_diff": 9,
  "marlin": 0,
  "marlin_diff": 0,
  "miatoll": 361,
  "miatoll_diff": 35,
  "payton": 567,
  "payton_diff": 1,
  "redfin": 25824,
  "redfin_diff": 8,
  "rosemary": 792,
  "rosemary_diff": 21,
  "sailfish": 0,
  "sailfish_diff": 0,
  "sargo": 11632,
  "sargo_diff": 35,
  "sunfish": 21603,
  "sunfish_diff": 95,
  "taimen": 12630,
  "taimen_diff": 12,
  "walleye": 0,
  "walleye_diff": 0
}