{
  "_date": "2025-01-05 20:16:40.908687",
  "_total": 84599,
  "_total_diff": 488,
  "barbet": 0,
  "barbet_diff": 0,
  "blueline": 20914,
  "blueline_diff": 152,
  "bonito": 3060,
  "bonito_diff": 3,
  "bramble": 3378,
  "bramble_diff": 38,
  "coral": 5090,
  "coral_diff": 19,
  "crosshatch": 15275,
  "crosshatch_diff": 60,
  "flame": 5797,
  "flame_diff": 75,
  "liber": 2911,
  "liber_diff": 11,
  "miatoll": 361,
  "miatoll_diff": 35,
  "redfin": 10064,
  "redfin_diff": 46,
  "rosemary": 792,
  "rosemary_diff": 21,
  "sargo": 5915,
  "sargo_diff": 59,
  "sunfish": 6409,
  "sunfish_diff": 17,
  "taimen": 5786,
  "taimen_diff": 8,
  "walleye": 0,
  "walleye_diff": 0
}