{
  "_date": "2025-09-13 20:28:56.396720",
  "_total": 286848,
  "_total_diff": 224,
  "barbet": 7249,
  "barbet_diff": 1,
  "blueline": 68630,
  "blueline_diff": 42,
  "bonito": 8824,
  "bonito_diff": 3,
  "bramble": 10731,
  "bramble_diff": 2,
  "coral": 21716,
  "coral_diff": 6,
  "crosshatch": 33349,
  "crosshatch_diff": 78,
  "flame": 17763,
  "flame_diff": 2,
  "hanoip": 9009,
  "hanoip_diff": 15,
  "liber": 8104,
  "liber_diff": 32,
  "marlin": 0,
  "marlin_diff": 0,
  "miatoll": 361,
  "miatoll_diff": 35,
  "payton": 944,
  "payton_diff": 1,
  "redfin": 34781,
  "redfin_diff": 13,
  "rosemary": 792,
  "rosemary_diff": 21,
  "sailfish": 0,
  "sailfish_diff": 0,
  "sargo": 15005,
  "sargo_diff": 5,
  "sunfish": 29204,
  "sunfish_diff": 23,
  "taimen": 21539,
  "taimen_diff": 1,
  "walleye": 0,
  "walleye_diff": 0
}