{
  "_date": "2025-09-12 20:31:09.050956",
  "_total": 286624,
  "_total_diff": 622,
  "barbet": 7248,
  "barbet_diff": 1,
  "blueline": 68588,
  "blueline_diff": 3,
  "bonito": 8821,
  "bonito_diff": 1,
  "bramble": 10729,
  "bramble_diff": 3,
  "coral": 21710,
  "coral_diff": 5,
  "crosshatch": 33271,
  "crosshatch_diff": 50,
  "flame": 17761,
  "flame_diff": 2,
  "hanoip": 8994,
  "hanoip_diff": 67,
  "liber": 8072,
  "liber_diff": 2,
  "marlin": 0,
  "marlin_diff": 0,
  "miatoll": 361,
  "miatoll_diff": 35,
  "payton": 943,
  "payton_diff": 1,
  "redfin": 34768,
  "redfin_diff": 7,
  "rosemary": 792,
  "rosemary_diff": 21,
  "sailfish": 0,
  "sailfish_diff": 0,
  "sargo": 15000,
  "sargo_diff": 12,
  "sunfish": 29181,
  "sunfish_diff": 17,
  "taimen": 21538,
  "taimen_diff": 464,
  "walleye": 0,
  "walleye_diff": 0
}