{
  "_date": "2025-02-28 20:31:59.688609",
  "_total": 130026,
  "_total_diff": 327,
  "barbet": 953,
  "barbet_diff": 2,
  "blueline": 32198,
  "blueline_diff": 54,
  "bonito": 3849,
  "bonito_diff": 12,
  "bramble": 5159,
  "bramble_diff": 14,
  "coral": 7408,
  "coral_diff": 5,
  "crosshatch": 19184,
  "crosshatch_diff": 7,
  "flame": 8171,
  "flame_diff": 4,
  "hanoip": 1691,
  "hanoip_diff": 2,
  "liber": 4276,
  "liber_diff": 1,
  "marlin": 0,
  "marlin_diff": 0,
  "miatoll": 361,
  "miatoll_diff": 35,
  "payton": 216,
  "payton_diff": 1,
  "redfin": 17935,
  "redfin_diff": 10,
  "rosemary": 792,
  "rosemary_diff": 21,
  "sailfish": 0,
  "sailfish_diff": 0,
  "sargo": 7858,
  "sargo_diff": 29,
  "sunfish": 13348,
  "sunfish_diff": 198,
  "taimen": 7780,
  "taimen_diff": 16,
  "walleye": 0,
  "walleye_diff": 0
}