{
  "_date": "2025-02-14 20:30:21.300256",
  "_total": 119568,
  "_total_diff": 1141,
  "barbet": 785,
  "barbet_diff": 93,
  "blueline": 30077,
  "blueline_diff": 157,
  "bonito": 3700,
  "bonito_diff": 24,
  "bramble": 4885,
  "bramble_diff": 8,
  "coral": 7156,
  "coral_diff": 205,
  "crosshatch": 17595,
  "crosshatch_diff": 16,
  "flame": 7943,
  "flame_diff": 53,
  "hanoip": 1216,
  "hanoip_diff": 3,
  "liber": 3491,
  "liber_diff": 4,
  "marlin": 0,
  "marlin_diff": 0,
  "miatoll": 361,
  "miatoll_diff": 35,
  "payton": 183,
  "payton_diff": 7,
  "redfin": 16698,
  "redfin_diff": 76,
  "rosemary": 792,
  "rosemary_diff": 21,
  "sailfish": 0,
  "sailfish_diff": 0,
  "sargo": 7472,
  "sargo_diff": 69,
  "sunfish": 10967,
  "sunfish_diff": 353,
  "taimen": 7400,
  "taimen_diff": 73,
  "walleye": 0,
  "walleye_diff": 0
}