{
  "_date": "2025-09-30 20:32:42.348991",
  "_total": 293850,
  "_total_diff": 481,
  "barbet": 7297,
  "barbet_diff": 36,
  "blueline": 69731,
  "blueline_diff": 109,
  "bonito": 9093,
  "bonito_diff": 1,
  "bramble": 10851,
  "bramble_diff": 8,
  "coral": 22160,
  "coral_diff": 2,
  "crosshatch": 34365,
  "crosshatch_diff": 21,
  "flame": 18123,
  "flame_diff": 4,
  "hanoip": 9628,
  "hanoip_diff": 47,
  "liber": 8304,
  "liber_diff": 3,
  "marlin": 0,
  "marlin_diff": 0,
  "miatoll": 361,
  "miatoll_diff": 35,
  "payton": 985,
  "payton_diff": 4,
  "redfin": 35722,
  "redfin_diff": 208,
  "rosemary": 792,
  "rosemary_diff": 21,
  "sailfish": 0,
  "sailfish_diff": 0,
  "sargo": 15876,
  "sargo_diff": 13,
  "sunfish": 29936,
  "sunfish_diff": 53,
  "taimen": 21779,
  "taimen_diff": 8,
  "walleye": 0,
  "walleye_diff": 0
}